opt3001/__init__.py
opt3001/opt3001.py
opt3001-1.1.4.dist-info/METADATA
opt3001-1.1.4.dist-info/WHEEL
opt3001-1.1.4.dist-info/top_level.txt
opt3001-1.1.4.dist-info/RECORD
