Metadata-Version: 2.1
Name: opt3001
Version: 1.1.4
Summary: Support library for the light sensor OPT3001 from Texas Instruments
Home-page: https://github.com/perryrh0dan/opt3001
Author: Thomas Poehlmann
Author-email: thomaspoehlmann96@googlemail.com
License: UNKNOWN
Platform: UNKNOWN
Classifier: Programming Language :: Python :: 3
Classifier: License :: OSI Approved :: MIT License
Classifier: Operating System :: OS Independent
